jumps/Jump_Tunnel.py
jumps/Jump_Tunnel_HIVE.py
jumps/SSH_Tunnel.py
jumps/__init__.py
jumps/cmd_config.py
jumps/demo.py
jumps/ftps_client.py
jumps/hive_client.py
jumps/jump_gui.py
jumps/jump_terminal.py
jumps/ssh_jump_hive.py
ssh_jump_hive-0.3.7.dist-info/METADATA
ssh_jump_hive-0.3.7.dist-info/RECORD
ssh_jump_hive-0.3.7.dist-info/WHEEL
ssh_jump_hive-0.3.7.dist-info/entry_points.txt
ssh_jump_hive-0.3.7.dist-info/top_level.txt
