Metadata-Version: 2.1
Name: ssh-jump-hive
Version: 0.3.7
Summary: ssh_jump_hive is a tools could  jump the jump machine  to connect hive get hive data to pandas dataframe
Home-page: https://github.com/mullerhai/sshjumphive
Author: mullerhai
Author-email: hai710459649@foxmail.com
Maintainer: muller helen
Maintainer-email: hai710459649@foxmail.com
License: Apache 2.0
Keywords: hive,ssh-tunnel,hfds,machine learning
Platform: all
Classifier: Programming Language :: Python :: 2.7
Classifier: Programming Language :: Python :: 3.4
Classifier: Programming Language :: Python :: 3.5
Classifier: Programming Language :: Python :: 3.6
Classifier: Development Status :: 4 - Beta
Classifier: Intended Audience :: Developers
Classifier: Natural Language :: English
Classifier: License :: OSI Approved :: Apache Software License
Classifier: Operating System :: OS Independent
Classifier: Programming Language :: Python
Classifier: Topic :: Scientific/Engineering
Requires-Dist: pandas (>=0.20.3)
Requires-Dist: PyHive (>=0.5.1)
Requires-Dist: paramiko (>=2.4.1)
Requires-Dist: selectors (>=0.0.14)
Requires-Dist: sasl (>=0.2.1)
Requires-Dist: thrift (>=0.11.0)
Requires-Dist: thrift-sasl (>=0.3.0)
Requires-Dist: hdfs (>=2.1.0)
Requires-Dist: sklearn-pandas (>=1.6.0)
Requires-Dist: scikit-learn (>=0.19.1)
Requires-Dist: click (>=6.7)
